setup.py
pyjasperclient/__init__.py
pyjasperclient/jasperclient.py
pyjasperclient.egg-info/PKG-INFO
pyjasperclient.egg-info/SOURCES.txt
pyjasperclient.egg-info/dependency_links.txt
pyjasperclient.egg-info/requires.txt
pyjasperclient.egg-info/top_level.txt