Metadata-Version: 1.0
Name: pyjasperclient
Version: 0.1
Summary: JasperServer SOAP client for Python
Home-page: https://launchpad.net/pyjasperclient
Author: Erdem Agaoglu
Author-email: erdem.agaoglu@gmail.com
License: ['apache']
Platform: UNKNOWN
